AsyncSocketPubSub/__init__.py
AsyncSocketPubSub/client.py
AsyncSocketPubSub/server.py
AsyncSocketPubSub-0.1.1.dist-info/METADATA
AsyncSocketPubSub-0.1.1.dist-info/WHEEL
AsyncSocketPubSub-0.1.1.dist-info/top_level.txt
AsyncSocketPubSub-0.1.1.dist-info/RECORD
