Metadata-Version: 2.1
Name: AsyncSocketPubSub
Version: 0.1.1
Requires-Dist: pubsub ==0.1.2
